nested_dataclasses/__init__.py
nested_dataclasses/mixins.py
nested_dataclasses/nested_dataclass.py
nested_dataclasses-0.2.dist-info/LICENSE
nested_dataclasses-0.2.dist-info/METADATA
nested_dataclasses-0.2.dist-info/WHEEL
nested_dataclasses-0.2.dist-info/top_level.txt
nested_dataclasses-0.2.dist-info/RECORD
