Metadata-Version: 2.1
Name: nested-dataclasses
Version: 0.2
Summary: Implements decorator `nested` that adds a parent and children to a dataclass.
Home-page: https://github.com/PDOK/nested-dataclasses
Author: Roel van den Berg
Author-email: roel.vandenberg@kadaster.nl
Keywords: nested-dataclasses
Classifier: Programming Language :: Python :: 3
License-File: LICENSE
